spectral_rhythm_detector/__init__.py
spectral_rhythm_detector/core.py
spectral_rhythm_detector/lfp_likelihood.py
spectral_rhythm_detector/simulate_LFP.py
spectral_rhythm_detector-0.1.0.dev0.dist-info/LICENSE
spectral_rhythm_detector-0.1.0.dev0.dist-info/METADATA
spectral_rhythm_detector-0.1.0.dev0.dist-info/WHEEL
spectral_rhythm_detector-0.1.0.dev0.dist-info/top_level.txt
spectral_rhythm_detector-0.1.0.dev0.dist-info/RECORD
